[{"br":"ArrowUp","br_rt":4073,"conf":"ArrowRight","conf_rt":192},{"br":"ArrowUp","br_rt":3000,"conf":"ArrowRight","conf_rt":180.00000000006},{"br":"ArrowUp","br_rt":3342.9999999999,"conf":"ArrowRight","conf_rt":229.00000000006},{"br":"ArrowUp","br_rt":3764.9999999999,"conf":"ArrowRight","conf_rt":231},{"br":"ArrowUp","br_rt":3842,"conf":"ArrowRight","conf_rt":160},{"br":"ArrowUp","br_rt":3244,"conf":"ArrowRight","conf_rt":200},{"br":"ArrowUp","br_rt":3436,"conf":"ArrowRight","conf_rt":180},{"br":"ArrowUp","br_rt":3136,"conf":"ArrowRight","conf_rt":196},{"br":"ArrowDown","br_rt":4582,"conf":"ArrowRight","conf_rt":140},{"br":"ArrowUp","br_rt":2710.0000000001,"conf":"ArrowRight","conf_rt":218.99999999994},{"br":"ArrowUp","br_rt":2781.0000000001,"conf":"ArrowRight","conf_rt":190.99999999994},{"br":"ArrowUp","br_rt":3254,"conf":"ArrowRight","conf_rt":187},{"br":"ArrowUp","br_rt":3117,"conf":"ArrowRight","conf_rt":189},{"br":"ArrowUp","br_rt":3269,"conf":"ArrowRight","conf_rt":181},{"br":"ArrowUp","br_rt":3733,"conf":"ArrowRight","conf_rt":156},{"br":"ArrowUp","br_rt":4137,"conf":"ArrowRight","conf_rt":156},{"br":"ArrowUp","br_rt":3808,"conf":"ArrowRight","conf_rt":184},{"br":"ArrowDown","br_rt":3375,"conf":"ArrowRight","conf_rt":168},{"br":"ArrowUp","br_rt":3974,"conf":"ArrowRight","conf_rt":168},{"br":"ArrowUp","br_rt":3182,"conf":"ArrowRight","conf_rt":164},{"br":"ArrowUp","br_rt":4047,"conf":"ArrowRight","conf_rt":144},{"br":"ArrowUp","br_rt":4052,"conf":"ArrowRight","conf_rt":132},{"br":"ArrowUp","br_rt":3421,"conf":"ArrowRight","conf_rt":168},{"br":"ArrowUp","br_rt":3721,"conf":"ArrowRight","conf_rt":176},{"br":"ArrowUp","br_rt":3701,"conf":"ArrowRight","conf_rt":166},{"br":"ArrowUp","br_rt":3950,"conf":"ArrowRight","conf_rt":212},{"br":"ArrowDown","br_rt":2752,"conf":"ArrowRight","conf_rt":164.00000000006},{"br":"ArrowUp","br_rt":3484.9999999999,"conf":"ArrowRight","conf_rt":180},{"br":"ArrowUp","br_rt":4209,"conf":"ArrowRight","conf_rt":190},{"br":"ArrowUp","br_rt":3180,"conf":"ArrowRight","conf_rt":152},{"br":"ArrowUp","br_rt":3665,"conf":"ArrowRight","conf_rt":228},{"br":"ArrowUp","br_rt":2969,"conf":"ArrowRight","conf_rt":164},{"br":"ArrowUp","br_rt":3110,"conf":"ArrowRight","conf_rt":144},{"br":"ArrowUp","br_rt":4109,"conf":"ArrowRight","conf_rt":188},{"br":"ArrowUp","br_rt":3409,"conf":"ArrowRight","conf_rt":135.00000000006},{"br":"ArrowDown","br_rt":3275.9999999999,"conf":"ArrowRight","conf_rt":168},{"br":"ArrowUp","br_rt":4238,"conf":"ArrowRight","conf_rt":101},{"br":"ArrowUp","br_rt":4086,"conf":"ArrowRight","conf_rt":169},{"br":"ArrowUp","br_rt":3396,"conf":"ArrowRight","conf_rt":192},{"br":"ArrowUp","br_rt":2670,"conf":"ArrowRight","conf_rt":164},{"br":"ArrowUp","br_rt":3151,"conf":"ArrowRight","conf_rt":164},{"br":"ArrowUp","br_rt":3811,"conf":"ArrowRight","conf_rt":200},{"br":"ArrowUp","br_rt":3613,"conf":"ArrowRight","conf_rt":176},{"br":"ArrowDown","br_rt":2666,"conf":"ArrowRight","conf_rt":228},{"br":"ArrowUp","br_rt":4426,"conf":"ArrowRight","conf_rt":319},{"br":"ArrowUp","br_rt":3628,"conf":"ArrowRight","conf_rt":199},{"br":"ArrowUp","br_rt":3813,"conf":"ArrowRight","conf_rt":160},{"br":"ArrowUp","br_rt":2486,"conf":"ArrowRight","conf_rt":151},{"br":"ArrowUp","br_rt":3060,"conf":"ArrowRight","conf_rt":172},{"br":"ArrowUp","br_rt":2891,"conf":"ArrowRight","conf_rt":217},{"br":"ArrowUp","br_rt":2808,"conf":"ArrowRight","conf_rt":297},{"br":"ArrowUp","br_rt":2946,"conf":"ArrowRight","conf_rt":241.00000000006},{"br":"ArrowDown","br_rt":3094.9999999999,"conf":"ArrowRight","conf_rt":205},{"br":"ArrowUp","br_rt":1933.0000000001,"conf":"ArrowRight","conf_rt":221},{"br":"ArrowUp","br_rt":3285.9999999999,"conf":"ArrowRight","conf_rt":260.00000000006},{"br":"ArrowUp","br_rt":2817,"conf":"ArrowRight","conf_rt":207.99999999994},{"br":"ArrowUp","br_rt":2088.0000000001,"conf":"ArrowRight","conf_rt":259.99999999994},{"br":"ArrowUp","br_rt":2603,"conf":"ArrowRight","conf_rt":169},{"br":"ArrowUp","br_rt":2357,"conf":"ArrowRight","conf_rt":200},{"br":"ArrowUp","br_rt":2682,"conf":"ArrowRight","conf_rt":184},{"br":"ArrowUp","br_rt":2176,"conf":"ArrowRight","conf_rt":300},{"br":"ArrowDown","br_rt":2343.0000000001,"conf":"ArrowRight","conf_rt":163.99999999994},{"br":"ArrowUp","br_rt":2819.0000000001,"conf":"ArrowRight","conf_rt":179.99999999994},{"br":"ArrowUp","br_rt":3503,"conf":"ArrowRight","conf_rt":173},{"br":"ArrowUp","br_rt":3971.0000000001,"conf":"ArrowRight","conf_rt":196},{"br":"ArrowUp","br_rt":3592.9999999999,"conf":"ArrowRight","conf_rt":160},{"br":"ArrowUp","br_rt":3038,"conf":"ArrowRight","conf_rt":168},{"br":"ArrowUp","br_rt":4144,"conf":"ArrowRight","conf_rt":176},{"br":"ArrowUp","br_rt":3700,"conf":"ArrowRight","conf_rt":155},{"br":"ArrowUp","br_rt":3015.0000000001,"conf":"ArrowRight","conf_rt":151.99999999988},{"br":"ArrowDown","br_rt":2986,"conf":"ArrowRight","conf_rt":204},{"br":"ArrowUp","br_rt":3307.0000000001,"conf":"ArrowRight","conf_rt":163.99999999988},{"br":"ArrowUp","br_rt":3475,"conf":"ArrowRight","conf_rt":180},{"br":"ArrowUp","br_rt":3467,"conf":"ArrowRight","conf_rt":188},{"br":"ArrowUp","br_rt":3323,"conf":"ArrowRight","conf_rt":192},{"br":"ArrowUp","br_rt":3314,"conf":"ArrowRight","conf_rt":213},{"br":"ArrowUp","br_rt":3677,"conf":"ArrowRight","conf_rt":212},{"br":"ArrowUp","br_rt":3724,"conf":"ArrowRight","conf_rt":196},{"br":"ArrowUp","br_rt":3167,"conf":"ArrowRight","conf_rt":272},{"br":"ArrowDown","br_rt":2895,"conf":"ArrowRight","conf_rt":196},{"br":"ArrowUp","br_rt":3199,"conf":"ArrowRight","conf_rt":176},{"br":"ArrowUp","br_rt":3242,"conf":"ArrowRight","conf_rt":139},{"br":"ArrowUp","br_rt":3369,"conf":"ArrowRight","conf_rt":172},{"br":"ArrowUp","br_rt":3457,"conf":"ArrowRight","conf_rt":216},{"br":"ArrowUp","br_rt":3172,"conf":"ArrowRight","conf_rt":224.00000000012},{"br":"ArrowUp","br_rt":3392.9999999999,"conf":"ArrowRight","conf_rt":216},{"br":"ArrowUp","br_rt":3359,"conf":"ArrowRight","conf_rt":211},{"br":"ArrowUp","br_rt":2919,"conf":"ArrowRight","conf_rt":208},{"br":"ArrowDown","br_rt":3143,"conf":"ArrowRight","conf_rt":224.00000000012},{"br":"ArrowUp","br_rt":2976,"conf":"ArrowRight","conf_rt":199.99999999988},{"br":"ArrowUp","br_rt":3562,"conf":"ArrowRight","conf_rt":244},{"br":"ArrowUp","br_rt":3381,"conf":"ArrowRight","conf_rt":172},{"br":"ArrowUp","br_rt":3469,"conf":"ArrowRight","conf_rt":180},{"br":"ArrowUp","br_rt":3820,"conf":"ArrowRight","conf_rt":228},{"br":"ArrowUp","br_rt":3375,"conf":"ArrowRight","conf_rt":228},{"br":"ArrowUp","br_rt":3967,"conf":"ArrowRight","conf_rt":204},{"br":"ArrowUp","br_rt":3225.0000000001,"conf":"ArrowRight","conf_rt":240.99999999988},{"br":"ArrowDown","br_rt":2960,"conf":"ArrowRight","conf_rt":192},{"br":"ArrowUp","br_rt":3383,"conf":"ArrowRight","conf_rt":156},{"br":"ArrowUp","br_rt":3139,"conf":"ArrowRight","conf_rt":179.00000000012},{"br":"ArrowUp","br_rt":3540.9999999999,"conf":"ArrowRight","conf_rt":185.00000000012},{"br":"ArrowUp","br_rt":3133.9999999999,"conf":"ArrowRight","conf_rt":204},{"br":"ArrowUp","br_rt":3429,"conf":"ArrowRight","conf_rt":152},{"br":"ArrowUp","br_rt":2836,"conf":"ArrowRight","conf_rt":264.00000000012},{"br":"ArrowUp","br_rt":2707,"conf":"ArrowRight","conf_rt":159.99999999988},{"br":"ArrowUp","br_rt":3285,"conf":"ArrowRight","conf_rt":203},{"br":"ArrowDown","br_rt":4029,"conf":"ArrowRight","conf_rt":195},{"br":"ArrowUp","br_rt":4494,"conf":"ArrowRight","conf_rt":124.00000000012},{"br":"ArrowUp","br_rt":2639.9999999999,"conf":"ArrowRight","conf_rt":139.00000000012},{"br":"ArrowUp","br_rt":2742.9999999999,"conf":"ArrowRight","conf_rt":168},{"br":"ArrowUp","br_rt":2908,"conf":"ArrowRight","conf_rt":172},{"br":"ArrowUp","br_rt":2774,"conf":"ArrowRight","conf_rt":272},{"br":"ArrowUp","br_rt":2832,"conf":"ArrowRight","conf_rt":212},{"br":"ArrowUp","br_rt":2916,"conf":"ArrowRight","conf_rt":129},{"br":"ArrowUp","br_rt":3230.0000000001,"conf":"ArrowRight","conf_rt":144.99999999988},{"br":"ArrowDown","br_rt":2094,"conf":"ArrowRight","conf_rt":209},{"br":"ArrowUp","br_rt":3768.0000000001,"conf":"ArrowRight","conf_rt":179.99999999988},{"br":"ArrowUp","br_rt":2489,"conf":"ArrowRight","conf_rt":119},{"br":"ArrowUp","br_rt":185,"conf":"ArrowRight","conf_rt":1978},{"br":"ArrowUp","br_rt":1379,"conf":"ArrowRight","conf_rt":116},{"br":"ArrowUp","br_rt":2429,"conf":"ArrowRight","conf_rt":154},{"br":"ArrowUp","br_rt":3046.0000000001,"conf":"ArrowRight","conf_rt":136.99999999988},{"br":"ArrowUp","br_rt":2493,"conf":"ArrowRight","conf_rt":174},{"br":"ArrowUp","br_rt":2499,"conf":"ArrowRight","conf_rt":163.00000000012},{"br":"ArrowDown","br_rt":2486.9999999999,"conf":"ArrowRight","conf_rt":168},{"br":"ArrowUp","br_rt":2768.0000000001,"conf":"ArrowRight","conf_rt":123.99999999988},{"br":"ArrowUp","br_rt":2587,"conf":"ArrowRight","conf_rt":137},{"br":"ArrowUp","br_rt":2490,"conf":"ArrowRight","conf_rt":180},{"br":"ArrowUp","br_rt":2235,"conf":"ArrowRight","conf_rt":132.00000000012},{"br":"ArrowUp","br_rt":2881.9999999999,"conf":"ArrowRight","conf_rt":96},{"br":"ArrowUp","br_rt":3191,"conf":"ArrowRight","conf_rt":101},{"br":"ArrowUp","br_rt":2745,"conf":"ArrowRight","conf_rt":135},{"br":"ArrowUp","br_rt":3690,"conf":"ArrowRight","conf_rt":156},{"br":"ArrowDown","br_rt":2743,"conf":"ArrowRight","conf_rt":174},{"br":"ArrowUp","br_rt":5234,"conf":"ArrowRight","conf_rt":42},{"br":"ArrowUp","br_rt":3499,"conf":"ArrowRight","conf_rt":158.00000000012},{"br":"ArrowUp","br_rt":3732.9999999999,"conf":"ArrowRight","conf_rt":132},{"br":"ArrowUp","br_rt":3196,"conf":"ArrowRight","conf_rt":184.00000000012},{"br":"ArrowUp","br_rt":3518.9999999999,"conf":"ArrowRight","conf_rt":120},{"br":"ArrowUp","br_rt":3679,"conf":"ArrowRight","conf_rt":148},{"br":"ArrowUp","br_rt":3095,"conf":"ArrowRight","conf_rt":172},{"br":"ArrowUp","br_rt":2977,"conf":"ArrowRight","conf_rt":196},{"br":"ArrowDown","br_rt":2744,"conf":"ArrowRight","conf_rt":156},{"br":"ArrowUp","br_rt":104,"conf":"ArrowRight","conf_rt":997},{"br":"ArrowUp","br_rt":2529,"conf":"ArrowRight","conf_rt":128},{"br":"ArrowUp","br_rt":3488,"conf":"ArrowRight","conf_rt":160.00000000012},{"br":"ArrowUp","br_rt":3554.9999999999,"conf":"ArrowRight","conf_rt":240},{"br":"ArrowUp","br_rt":3252,"conf":"ArrowRight","conf_rt":88},{"br":"ArrowUp","br_rt":3222,"conf":"ArrowRight","conf_rt":140},{"br":"ArrowUp","br_rt":3119,"conf":"ArrowRight","conf_rt":180},{"br":"ArrowUp","br_rt":3487,"conf":"ArrowRight","conf_rt":192},{"br":"ArrowDown","br_rt":2632,"conf":"ArrowRight","conf_rt":148.00000000012},{"br":"ArrowUp","br_rt":3502.9999999999,"conf":"ArrowRight","conf_rt":105},{"br":"ArrowUp","br_rt":3732,"conf":"ArrowRight","conf_rt":152},{"br":"ArrowUp","br_rt":3077,"conf":"ArrowRight","conf_rt":168},{"br":"ArrowUp","br_rt":3433,"conf":"ArrowRight","conf_rt":120},{"br":"ArrowUp","br_rt":3453,"conf":"ArrowRight","conf_rt":196},{"br":"ArrowUp","br_rt":3114,"conf":"ArrowRight","conf_rt":140},{"br":"ArrowUp","br_rt":3493,"conf":"ArrowRight","conf_rt":128},{"br":"ArrowUp","br_rt":3713,"conf":"ArrowRight","conf_rt":136.00000000012},{"br":"ArrowDown","br_rt":3152.9999999999,"conf":"ArrowRight","conf_rt":148},{"br":"ArrowUp","br_rt":3347,"conf":"ArrowRight","conf_rt":140},{"br":"ArrowUp","br_rt":3880,"conf":"ArrowRight","conf_rt":72},{"br":"ArrowUp","br_rt":3223,"conf":"ArrowRight","conf_rt":160},{"br":"ArrowUp","br_rt":3682,"conf":"ArrowRight","conf_rt":157.00000000012},{"br":"ArrowUp","br_rt":3294.9999999999,"conf":"ArrowRight","conf_rt":84},{"br":"ArrowUp","br_rt":2869,"conf":"ArrowRight","conf_rt":196},{"br":"ArrowUp","br_rt":3556.0000000001,"conf":"ArrowRight","conf_rt":175.99999999988},{"br":"ArrowUp","br_rt":3307,"conf":"ArrowRight","conf_rt":155},{"br":"ArrowDown","br_rt":2336,"conf":"ArrowRight","conf_rt":208},{"br":"ArrowUp","br_rt":2443.0000000001,"conf":"ArrowRight","conf_rt":192.99999999988},{"br":"ArrowUp","br_rt":3311,"conf":"ArrowRight","conf_rt":120},{"br":"ArrowUp","br_rt":2867,"conf":"ArrowRight","conf_rt":156},{"br":"ArrowUp","br_rt":2871,"conf":"ArrowRight","conf_rt":148},{"br":"ArrowUp","br_rt":3079.0000000001,"conf":"ArrowRight","conf_rt":156.99999999988},{"br":"ArrowUp","br_rt":3440,"conf":"ArrowRight","conf_rt":152},{"br":"ArrowUp","br_rt":2968,"conf":"ArrowRight","conf_rt":204},{"br":"ArrowUp","br_rt":2941,"conf":"ArrowRight","conf_rt":132},{"br":"ArrowDown","br_rt":3082,"conf":"ArrowRight","conf_rt":160},{"br":"ArrowUp","br_rt":3005,"conf":"ArrowRight","conf_rt":156},{"br":"ArrowUp","br_rt":3345,"conf":"ArrowRight","conf_rt":112},{"br":"ArrowUp","br_rt":3312,"conf":"ArrowRight","conf_rt":188},{"br":"ArrowUp","br_rt":2793,"conf":"ArrowRight","conf_rt":105},{"br":"ArrowUp","br_rt":2789,"conf":"ArrowRight","conf_rt":192},{"br":"ArrowUp","br_rt":2885,"conf":"ArrowRight","conf_rt":191},{"br":"ArrowUp","br_rt":2649,"conf":"ArrowRight","conf_rt":200},{"br":"ArrowUp","br_rt":2799,"conf":"ArrowRight","conf_rt":150},{"br":"ArrowDown","br_rt":108,"conf":"ArrowRight","conf_rt":939},{"br":"ArrowUp","br_rt":3052,"conf":"ArrowRight","conf_rt":172.00000000012},{"br":"ArrowUp","br_rt":3277.9999999999,"conf":"ArrowRight","conf_rt":148},{"br":"ArrowUp","br_rt":3538,"conf":"ArrowRight","conf_rt":129},{"br":"ArrowUp","br_rt":3375,"conf":"ArrowRight","conf_rt":92},{"br":"ArrowUp","br_rt":3200,"conf":"ArrowRight","conf_rt":195},{"br":"ArrowUp","br_rt":2127.0000000001,"conf":"ArrowRight","conf_rt":193.99999999988},{"br":"ArrowUp","br_rt":1941,"conf":"ArrowRight","conf_rt":203},{"br":"ArrowUp","br_rt":3119,"conf":"ArrowRight","conf_rt":72},{"br":"ArrowDown","br_rt":3373,"conf":"ArrowRight","conf_rt":131.00000000012},{"br":"ArrowUp","br_rt":2916.9999999999,"conf":"ArrowRight","conf_rt":168},{"br":"ArrowUp","br_rt":2692,"conf":"ArrowRight","conf_rt":47},{"br":"ArrowUp","br_rt":2999,"conf":"ArrowRight","conf_rt":128},{"br":"ArrowUp","br_rt":2623,"conf":"ArrowRight","conf_rt":121},{"br":"ArrowUp","br_rt":2972,"conf":"ArrowRight","conf_rt":165.00000000012},{"br":"ArrowUp","br_rt":2871.9999999999,"conf":"ArrowRight","conf_rt":168},{"br":"ArrowUp","br_rt":2750,"conf":"ArrowRight","conf_rt":101},{"br":"ArrowUp","br_rt":2731,"conf":"ArrowRight","conf_rt":136},{"br":"ArrowDown","br_rt":2394,"conf":"ArrowRight","conf_rt":152},{"br":"ArrowUp","br_rt":2963,"conf":"ArrowRight","conf_rt":100},{"br":"ArrowUp","br_rt":2605,"conf":"ArrowRight","conf_rt":112},{"br":"ArrowUp","br_rt":3042,"conf":"ArrowRight","conf_rt":169},{"br":"ArrowUp","br_rt":2792,"conf":"ArrowRight","conf_rt":132},{"br":"ArrowUp","br_rt":3853.0000000001,"conf":"ArrowRight","conf_rt":147.99999999988},{"br":"ArrowUp","br_rt":3380,"conf":"ArrowRight","conf_rt":116.00000000012},{"br":"ArrowUp","br_rt":2745.9999999999,"conf":"ArrowRight","conf_rt":172},{"br":"ArrowUp","br_rt":2749,"conf":"ArrowRight","conf_rt":229},{"br":"ArrowDown","br_rt":3033,"conf":"ArrowRight","conf_rt":161},{"br":"ArrowUp","br_rt":3156,"conf":"ArrowRight","conf_rt":163.00000000012},{"br":"ArrowUp","br_rt":3252.9999999999,"conf":"ArrowRight","conf_rt":184},{"br":"ArrowUp","br_rt":3654.9999999999,"conf":"ArrowRight","conf_rt":132.00000000012},{"br":"ArrowUp","br_rt":3147.9999999999,"conf":"ArrowRight","conf_rt":181.00000000012},{"br":"ArrowUp","br_rt":2903,"conf":"ArrowRight","conf_rt":148.00000000012},{"br":"ArrowUp","br_rt":3042.9999999999,"conf":"ArrowRight","conf_rt":221},{"br":"ArrowUp","br_rt":2909.0000000001,"conf":"ArrowRight","conf_rt":144},{"br":"ArrowUp","br_rt":3055.9999999998,"conf":"ArrowRight","conf_rt":209.00000000012},{"br":"ArrowDown","br_rt":2826,"conf":"ArrowRight","conf_rt":175},{"br":"ArrowUp","br_rt":2268,"conf":"ArrowRight","conf_rt":164},{"br":"ArrowUp","br_rt":2829,"conf":"ArrowRight","conf_rt":184.00000000023},{"br":"ArrowUp","br_rt":3255.9999999998,"conf":"ArrowRight","conf_rt":148.00000000023},{"br":"ArrowUp","br_rt":2846.9999999998,"conf":"ArrowRight","conf_rt":160},{"br":"ArrowUp","br_rt":3728,"conf":"ArrowRight","conf_rt":152},{"br":"ArrowUp","br_rt":3851,"conf":"ArrowRight","conf_rt":140},{"br":"ArrowUp","br_rt":3300,"conf":"ArrowRight","conf_rt":190},{"br":"ArrowUp","br_rt":2674,"conf":"ArrowRight","conf_rt":184},{"br":"ArrowDown","br_rt":2483,"conf":"ArrowRight","conf_rt":88},{"br":"ArrowUp","br_rt":3366,"conf":"ArrowRight","conf_rt":148},{"br":"ArrowUp","br_rt":3513,"conf":"ArrowRight","conf_rt":156},{"br":"ArrowUp","br_rt":3183,"conf":"ArrowRight","conf_rt":136},{"br":"ArrowUp","br_rt":3968,"conf":"ArrowRight","conf_rt":174},{"br":"ArrowUp","br_rt":3387,"conf":"ArrowRight","conf_rt":164},{"br":"ArrowUp","br_rt":3338,"conf":"ArrowRight","conf_rt":192},{"br":"ArrowUp","br_rt":3248,"conf":"ArrowRight","conf_rt":192},{"br":"ArrowUp","br_rt":3579,"conf":"ArrowRight","conf_rt":160},{"br":"ArrowDown","br_rt":2989,"conf":"ArrowRight","conf_rt":140},{"br":"ArrowUp","br_rt":5995,"conf":"ArrowRight","conf_rt":175.00000000023},{"br":"ArrowUp","br_rt":3599.9999999998,"conf":"ArrowRight","conf_rt":175},{"br":"ArrowUp","br_rt":3520,"conf":"ArrowRight","conf_rt":172},{"br":"ArrowUp","br_rt":3342,"conf":"ArrowRight","conf_rt":220.00000000023},{"br":"ArrowUp","br_rt":3332.9999999998,"conf":"ArrowRight","conf_rt":168},{"br":"ArrowUp","br_rt":3225,"conf":"ArrowRight","conf_rt":121},{"br":"ArrowUp","br_rt":3291,"conf":"ArrowRight","conf_rt":161},{"br":"ArrowUp","br_rt":3389,"conf":"ArrowRight","conf_rt":124},{"br":"ArrowDown","br_rt":3036,"conf":"ArrowRight","conf_rt":164},{"br":"ArrowUp","br_rt":3626,"conf":"ArrowRight","conf_rt":126},{"br":"ArrowUp","br_rt":3410,"conf":"ArrowRight","conf_rt":144},{"br":"ArrowUp","br_rt":3876,"conf":"ArrowRight","conf_rt":144},{"br":"ArrowUp","br_rt":3768.0000000002,"conf":"ArrowRight","conf_rt":139.99999999977},{"br":"ArrowUp","br_rt":3265,"conf":"ArrowRight","conf_rt":136},{"br":"ArrowUp","br_rt":4518,"conf":"ArrowRight","conf_rt":98},{"br":"ArrowUp","br_rt":3379,"conf":"ArrowRight","conf_rt":120},{"br":"ArrowUp","br_rt":356,"conf":"ArrowRight","conf_rt":1608},{"br":"ArrowDown","br_rt":3133,"conf":"ArrowRight","conf_rt":238},{"br":"ArrowUp","br_rt":3755,"conf":"ArrowRight","conf_rt":140},{"br":"ArrowUp","br_rt":3042,"conf":"ArrowRight","conf_rt":169},{"br":"ArrowUp","br_rt":2731,"conf":"ArrowRight","conf_rt":152}]